MANIFEST.in
README.md
setup.cfg
setup.py
chartflo/__init__.py
chartflo/admin.py
chartflo/altair.py
chartflo/apps.py
chartflo/models.py
chartflo/urls.py
chartflo/utils.py
chartflo/views.py
chartflo/migrations/0001_initial.py
chartflo/migrations/0002_auto_20180913_1516.py
chartflo/migrations/__init__.py
chartflo/static/Responsive-2.2.2/css/responsive.bootstrap.css
chartflo/static/Responsive-2.2.2/css/responsive.bootstrap.min.css
chartflo/static/Responsive-2.2.2/css/responsive.bootstrap4.css
chartflo/static/Responsive-2.2.2/css/responsive.bootstrap4.min.css
chartflo/static/Responsive-2.2.2/css/responsive.dataTables.css
chartflo/static/Responsive-2.2.2/css/responsive.dataTables.min.css
chartflo/static/Responsive-2.2.2/css/responsive.foundation.css
chartflo/static/Responsive-2.2.2/css/responsive.foundation.min.css
chartflo/static/Responsive-2.2.2/css/responsive.jqueryui.css
chartflo/static/Responsive-2.2.2/css/responsive.jqueryui.min.css
chartflo/static/Responsive-2.2.2/css/responsive.semanticui.css
chartflo/static/Responsive-2.2.2/css/responsive.semanticui.min.css
chartflo/static/Responsive-2.2.2/js/dataTables.responsive.js
chartflo/static/Responsive-2.2.2/js/dataTables.responsive.min.js
chartflo/static/Responsive-2.2.2/js/responsive.bootstrap.js
chartflo/static/Responsive-2.2.2/js/responsive.bootstrap.min.js
chartflo/static/Responsive-2.2.2/js/responsive.bootstrap4.js
chartflo/static/Responsive-2.2.2/js/responsive.bootstrap4.min.js
chartflo/static/Responsive-2.2.2/js/responsive.foundation.js
chartflo/static/Responsive-2.2.2/js/responsive.foundation.min.js
chartflo/static/Responsive-2.2.2/js/responsive.jqueryui.js
chartflo/static/Responsive-2.2.2/js/responsive.jqueryui.min.js
chartflo/static/Responsive-2.2.2/js/responsive.semanticui.js
chartflo/static/Responsive-2.2.2/js/responsive.semanticui.min.js
chartflo/static/css/bokeh.min.css
chartflo/static/css/buefy.min.css
chartflo/static/css/chartflo.css
chartflo/static/css/datatables.min.css
django_chartflo.egg-info/PKG-INFO
django_chartflo.egg-info/SOURCES.txt
django_chartflo.egg-info/dependency_links.txt
django_chartflo.egg-info/not-zip-safe
django_chartflo.egg-info/requires.txt
django_chartflo.egg-info/top_level.txt