Metadata-Version: 1.1
Name: django-chartflo
Version: 0.5.2
Summary: Charts for the lazy ones in Django
Home-page: https://github.com/synw/django-chartflo
Author: synw
Author-email: synwe@yahoo.com
License: UNKNOWN
Download-URL: https://github.com/synw/django-chartflo/releases/tag/0.5.2
Keywords: charts,dashboards,reporting
Platform: UNKNOWN
Classifier: Development Status :: 3 - Alpha
Classifier: Framework :: Django :: 1.11
Classifier: Intended Audience :: Developers
Classifier: License :: OSI Approved :: MIT License
Classifier: Programming Language :: Python :: 3.6
